LICENSE
README.rst
setup.cfg
setup.py
tpPyUtils/__init__.py
tpPyUtils/__version__.py
tpPyUtils/attributes.py
tpPyUtils/code.py
tpPyUtils/config.py
tpPyUtils/dcc.py
tpPyUtils/debug.py
tpPyUtils/decorators.py
tpPyUtils/download.py
tpPyUtils/email.py
tpPyUtils/enum.py
tpPyUtils/fileio.py
tpPyUtils/folder.py
tpPyUtils/importer.py
tpPyUtils/interfaces.py
tpPyUtils/jsonio.py
tpPyUtils/language.py
tpPyUtils/log.py
tpPyUtils/mathlib.py
tpPyUtils/name.py
tpPyUtils/octree.py
tpPyUtils/osplatform.py
tpPyUtils/path.py
tpPyUtils/profiler.py
tpPyUtils/psd.py
tpPyUtils/python.py
tpPyUtils/reloader.py
tpPyUtils/security.py
tpPyUtils/settings.py
tpPyUtils/sort.py
tpPyUtils/strings.py
tpPyUtils/timedate.py
tpPyUtils/timers.py
tpPyUtils/version.py
tpPyUtils/web.py
tpPyUtils/win32.py
tpPyUtils/yamlio.py
tppyutils.egg-info/PKG-INFO
tppyutils.egg-info/SOURCES.txt
tppyutils.egg-info/dependency_links.txt
tppyutils.egg-info/not-zip-safe
tppyutils.egg-info/requires.txt
tppyutils.egg-info/top_level.txt