Metadata-Version: 2.1
Name: tppyutils
Version: 0.0.22
Summary: Collection of Python utilities modules to work with Python and DCCs
Home-page: https://github.com/tpoveda/tpPyUtils
Author: Tomas Poveda
Author-email: tpovedatd@gmail.com
License: MIT
Platform: UNKNOWN
Provides-Extra: dev
Provides-Extra: test
